LICENSE
MANIFEST.in
README.md
setup.py
webseer/__init__.py
webseer/seer.py
webseer.egg-info/PKG-INFO
webseer.egg-info/SOURCES.txt
webseer.egg-info/dependency_links.txt
webseer.egg-info/requires.txt
webseer.egg-info/top_level.txt
webseer/llm/__init__.py
webseer/llm/llm_filter.py
webseer/llm/readhtml.py
webseer/scraper/__init__.py
webseer/scraper/playwright_crawler.py
webseer/scraper/selectors_config.py
webseer/scraper/xpath_extractor.py
webseer/store/__init__.py
webseer/store/db_connect.py
webseer/store/db_writer.py
webseer/utils/__init__.py
webseer/utils/prompts.py
webseer/utils/util.py