Metadata-Version: 2.4
Name: webseer
Version: 0.1.3
Summary: Webseer 是一个语义驱动的网络情报者，根据用户定义的关注点，从互联网上主动搜集并结构化相关信息。与传统爬虫不同，Webseer 以目标为导向地探索网络，理解内容、追踪语义，而不是盲目抓取所有链接。
Home-page: https://github.com/AgBigdataLab/Webseer
Author: Jie Huang
Author-email: hjie97bi@gmail.com
License: MIT
Keywords: python,windows,mac,linux,Webseer,crawl,scraper,LLM,playwright
Classifier: Programming Language :: Python
Classifier: Programming Language :: Python :: 3
Classifier: Programming Language :: Python :: 3.10
Classifier: Programming Language :: Python :: 3.11
Classifier: Programming Language :: Python :: 3.12
Classifier: Programming Language :: Python :: Implementation :: CPython
Classifier: Programming Language :: Python :: Implementation :: PyPy
Classifier: Framework :: Jupyter
Classifier: Operating System :: MacOS
Classifier: Operating System :: Microsoft
Classifier: Operating System :: Microsoft :: Windows
Classifier: Operating System :: Microsoft :: Windows :: Windows 10
Classifier: Operating System :: Microsoft :: Windows :: Windows 11
Classifier: Operating System :: Unix
Requires-Python: >=3.10.0
License-File: LICENSE
Requires-Dist: transformers>=4.51.3
Requires-Dist: chunk-factory==0.1.5
Requires-Dist: fake_useragent>=2.2.0
Requires-Dist: playwright>=1.52.0
Requires-Dist: numpy==1.26.4
Requires-Dist: pymysql==1.1.1
Requires-Dist: json_repair>=0.44.1
Requires-Dist: validators>=0.35.0
Requires-Dist: langdetect>=1.0.9
Dynamic: author
Dynamic: author-email
Dynamic: classifier
Dynamic: description
Dynamic: description-content-type
Dynamic: home-page
Dynamic: keywords
Dynamic: license
Dynamic: license-file
Dynamic: requires-dist
Dynamic: requires-python
Dynamic: summary
